netsome/__init__.py
netsome/_converters/__init__.py
netsome/_converters/bgp.py
netsome/_converters/ipv4.py
netsome/_converters/ipv6.py
netsome/constants.py
netsome/types/__init__.py
netsome/types/bgp.py
netsome/types/interfaces.py
netsome/types/ipv4.py
netsome/types/ipv6.py
netsome/types/mac.py
netsome/types/vlans.py
netsome/validators/__init__.py
netsome/validators/bgp.py
netsome/validators/ipv4.py
netsome/validators/ipv6.py
netsome/validators/mac.py
netsome/validators/vlans.py
netsome-0.4.4.dist-info/METADATA
netsome-0.4.4.dist-info/WHEEL
netsome-0.4.4.dist-info/licenses/LICENSE
netsome-0.4.4.dist-info/RECORD
