Metadata-Version: 2.4
Name: netsome
Version: 0.4.4
Summary: The one and only library to make your network code handsome
License: X11-distribute-modifications-variant
License-File: LICENSE
Keywords: library,network
Author: kuderr
Author-email: dakudryavcev@gmail.com
Requires-Python: >=3.10,<4.0
Classifier: Development Status :: 5 - Production/Stable
Classifier: License :: Other/Proprietary License
Classifier: Programming Language :: Python :: 3
Classifier: Programming Language :: Python :: 3.10
Classifier: Programming Language :: Python :: 3.11
Classifier: Programming Language :: Python :: 3.12
Classifier: Programming Language :: Python :: 3.13
Classifier: Programming Language :: Python :: 3.14
Classifier: Topic :: Software Development :: Libraries
Classifier: Topic :: System :: Networking
Project-URL: Bug Tracker, https://github.com/kuderr/netsome/issues
Project-URL: Homepage, https://github.com/kuderr/netsome
Project-URL: Repository, https://github.com/kuderr/netsome
